{
  "About the internship": "💼",
  "Timing and dates": "📅",
  "NOC (No Objection Certificate)": "📄",
  "Selection, offer letter, and certificate": "📜",
  "Work, mentorship, and projects": "💻",
  "Code of conduct — communication channels": "📋",
  "Interviews Related": "🎤",
  "Certificate": "🏆",
  "Rosetta — your internship journal": "📔",
  "Phase 1 — coursework, Vibe LMS, and live sessions": "📚",
  "Spurti Points": "⭐",
  "ViBe Platform": "🎯",
  "Team Formation": "👥",
  "Yaksha Chat Related": "💬",
  "Discourse Related": "💭",
  "Uncategorized": "📌"
}